tsp_tools/__init__.py
tsp_tools/py.typed
tsp_tools-0.3.2.dist-info/METADATA
tsp_tools-0.3.2.dist-info/WHEEL
tsp_tools-0.3.2.dist-info/licenses/LICENSE
tsp_tools-0.3.2.dist-info/RECORD
