Metadata-Version: 2.3
Name: tsp-tools
Version: 0.3.2
Summary: `tsp-tools` is a package for Traveling Salesman Problem for Python.
Project-URL: homepage, https://github.com/SaitoTsutomu/tsp-tools
Author-email: Saito Tsutomu <tsutomu7@hotmail.co.jp>
License: Apache-2.0
License-File: LICENSE
Classifier: Development Status :: 1 - Planning
Classifier: License :: OSI Approved :: Apache Software License
Classifier: Programming Language :: Python
Classifier: Topic :: Scientific/Engineering
Classifier: Topic :: Software Development
Requires-Python: >=3.12
Requires-Dist: more-itertools>=10.5.0
Requires-Dist: pandas>=2.2.3
Requires-Dist: pulp>=2.9.0
